corl/__init__.py
corl/agents/__init__.py
corl/agents/base_agent.py
corl/agents/non_trainable/__init__.py
corl/agents/non_trainable/noop.py
corl/agents/non_trainable/random_action.py
corl/agents/simple_multi_platform_agent.py
corl/config/policy/ppo/default_config.yml
corl/config/policy/random_action.yml
corl/config/policy/scripted_action.yml
corl/config/streamlit_app/default_streamlit_config.yml
corl/config/streamlit_app/docking1d_streamlit_config.yml
corl/config/streamlit_app/pong_streamlit_config.yml
corl/config/tasks/docking_1d/agents/docking1d_agent.yml
corl/config/tasks/docking_1d/environments/docking1d_env.yml
corl/config/tasks/docking_1d/evaluation/alerts/base_alerts.yml
corl/config/tasks/docking_1d/evaluation/launch/eval_1d_docking.yml
corl/config/tasks/docking_1d/evaluation/launch/metrics_gen_1d_docking.yml
corl/config/tasks/docking_1d/evaluation/launch/pipeline_1d_docking.yml
corl/config/tasks/docking_1d/evaluation/launch/storage_acedt_1d_docking.yml
corl/config/tasks/docking_1d/evaluation/launch/visualize_1d_docking.yml
corl/config/tasks/docking_1d/evaluation/metrics/1d_docking.yml
corl/config/tasks/docking_1d/evaluation/test_cases_config/docking1d_tests.yml
corl/config/tasks/docking_1d/experiments/docking_1d.yml
corl/config/tasks/docking_1d/platforms/docking1d_platform.yml
corl/config/tasks/docking_1d/ray_config.yml
corl/config/tasks/docking_1d/rllib_config.yml
corl/config/tasks/docking_1d/tasks/docking1d_task.yml
corl/config/tasks/docking_1d/tune_config.yml
corl/config/tasks/gymnasium/agents/baseline_dones.yml
corl/config/tasks/gymnasium/agents/baseline_epp.yml
corl/config/tasks/gymnasium/agents/baseline_rewards.yml
corl/config/tasks/gymnasium/agents/gymnasium_agent.yml
corl/config/tasks/gymnasium/agents/gymnasium_agent_dict_wrapper.yml
corl/config/tasks/gymnasium/agents/gymnasium_agent_noop.yml
corl/config/tasks/gymnasium/agents/gymnasium_agent_noop_ctrl.yml
corl/config/tasks/gymnasium/agents/gymnasium_agent_repeated.yml
corl-3.16.2.dist-info/LICENSE.md
corl-3.16.2.dist-info/METADATA
corl-3.16.2.dist-info/WHEEL
corl-3.16.2.dist-info/entry_points.txt
corl-3.16.2.dist-info/RECORD
