Metadata-Version: 2.1
Name: corl
Version: 3.16.2
Summary: Core ACT3 Reinforcement Learning (RL) Library - Core framework and base implementations of common things such as controllers, glues, observes, sensors, evaluation, and etc
Home-page: https://github.com/act3-ace/CoRL
Keywords: Deep,Reinforcement,Learning,CoRL,act3,ACT3
Author: Benjamin K Heiner
Author-email: benjamin.heiner@us.af.mil
Maintainer: Benjamin K Heiner
Maintainer-email: benjamin.heiner@us.af.mil
Requires-Python: >=3.10,<3.12
Classifier: Operating System :: OS Independent
Classifier: Programming Language :: Python :: 3
Classifier: Programming Language :: Python :: 3.10
Classifier: Programming Language :: Python :: 3.11
Requires-Dist: GitPython (==3.1.41)
Requires-Dist: async_timeout (>=4.0.3,<5.0.0)
Requires-Dist: codetiming (>=1.4.0,<2.0.0)
Requires-Dist: deepmerge (==0.3.0)
Requires-Dist: fastapi (>=0.104.1,<0.105.0)
Requires-Dist: flatten-dict (==0.4.1)
Requires-Dist: gymnasium (==0.28.1)
Requires-Dist: h5py (>=3.7)
Requires-Dist: jsonargparse[argcomplete,signatures] (>=4,<5)
Requires-Dist: jsonlines (>=4.0.0,<5.0.0)
Requires-Dist: matplotlib (>=3.7.2,<4.0.0)
Requires-Dist: numpy (>=1.24.0,<2.0.0)
Requires-Dist: numpy-ringbuffer (>=0.2.2,<0.3.0)
Requires-Dist: plotly (>=5.14.1,<6.0.0)
Requires-Dist: pydantic (>=2.5.0,<3.0.0)
Requires-Dist: pygame (>=2.1.2,<3.0.0)
Requires-Dist: pygifsicle (>=1.0.7,<2.0.0)
Requires-Dist: ray[all] (>=2.9.0,<2.10.0)
Requires-Dist: scipy (>=1.10.1,<2.0.0)
Requires-Dist: stqdm (>=0.0.5,<0.0.6)
Requires-Dist: streamlit (>=1.30.0,<2.0.0)
Requires-Dist: tabulate (>=0.9.0,<0.10.0)
Requires-Dist: tensorboard (>=2.10,<3.0)
Requires-Dist: tensorflow (==2.15.0)
Requires-Dist: tensorflow-probability (>=0.23.0,<0.24.0)
Requires-Dist: types-tabulate (>=0.9.0.2,<0.10.0.0)
Requires-Dist: uvicorn (>=0.24.0.post1,<0.25.0)
Project-URL: Documentation, https://github.com/act3-ace/CoRL
Project-URL: Repository, https://github.com/act3-ace/CoRL
